wowlib/__init__.py
wowlib/color.py
wowlib/common.py
wowlib/convert.py
wowlib/excel2bcc.py
wowlib/excel2cs.py
wowlib/excel2dbc.py
wowlib/excel2h.py
wowlib/excel2lua.py
wowlib/excel2ts.py
wowlib/excelverify.py
wowlib-1.6.0.dist-info/LICENSE
wowlib-1.6.0.dist-info/METADATA
wowlib-1.6.0.dist-info/WHEEL
wowlib-1.6.0.dist-info/top_level.txt
wowlib-1.6.0.dist-info/RECORD
