Metadata-Version: 2.1
Name: wowlib
Version: 1.6.0
Summary: Excel convert tools for wow studio
Home-page: https://www.q1.com
Author: peakgao
Author-email: peakgao163@163.com
License: MIT
Platform: UNKNOWN
Classifier: Programming Language :: Python :: 3
Classifier: License :: OSI Approved :: MIT License
Classifier: Operating System :: OS Independent
Requires-Dist: xlrd
